odoo8_addon_sale_payment_method_automatic_workflow-8.0.1.0.0.99.dev21-py3.8-nspkg.pth
odoo_addons/sale_payment_method_automatic_workflow/README.rst
odoo_addons/sale_payment_method_automatic_workflow/__init__.py
odoo_addons/sale_payment_method_automatic_workflow/__openerp__.py
odoo_addons/sale_payment_method_automatic_workflow/i18n/ar.po
odoo_addons/sale_payment_method_automatic_workflow/i18n/bg.po
odoo_addons/sale_payment_method_automatic_workflow/i18n/bs.po
odoo_addons/sale_payment_method_automatic_workflow/i18n/ca.po
odoo_addons/sale_payment_method_automatic_workflow/i18n/cs.po
odoo_addons/sale_payment_method_automatic_workflow/i18n/de.po
odoo_addons/sale_payment_method_automatic_workflow/i18n/el_GR.po
odoo_addons/sale_payment_method_automatic_workflow/i18n/en_GB.po
odoo_addons/sale_payment_method_automatic_workflow/i18n/es.po
odoo_addons/sale_payment_method_automatic_workflow/i18n/es_CR.po
odoo_addons/sale_payment_method_automatic_workflow/i18n/es_EC.po
odoo_addons/sale_payment_method_automatic_workflow/i18n/es_ES.po
odoo_addons/sale_payment_method_automatic_workflow/i18n/es_MX.po
odoo_addons/sale_payment_method_automatic_workflow/i18n/es_PE.po
odoo_addons/sale_payment_method_automatic_workflow/i18n/et.po
odoo_addons/sale_payment_method_automatic_workflow/i18n/fi.po
odoo_addons/sale_payment_method_automatic_workflow/i18n/fr.po
odoo_addons/sale_payment_method_automatic_workflow/i18n/fr_CH.po
odoo_addons/sale_payment_method_automatic_workflow/i18n/gl.po
odoo_addons/sale_payment_method_automatic_workflow/i18n/hr.po
odoo_addons/sale_payment_method_automatic_workflow/i18n/hr_HR.po
odoo_addons/sale_payment_method_automatic_workflow/i18n/hu.po
odoo_addons/sale_payment_method_automatic_workflow/i18n/id.po
odoo_addons/sale_payment_method_automatic_workflow/i18n/it.po
odoo_addons/sale_payment_method_automatic_workflow/i18n/ja.po
odoo_addons/sale_payment_method_automatic_workflow/i18n/lt.po
odoo_addons/sale_payment_method_automatic_workflow/i18n/mk.po
odoo8_addon_sale_payment_method_automatic_workflow-8.0.1.0.0.99.dev21.dist-info/METADATA
odoo8_addon_sale_payment_method_automatic_workflow-8.0.1.0.0.99.dev21.dist-info/WHEEL
odoo8_addon_sale_payment_method_automatic_workflow-8.0.1.0.0.99.dev21.dist-info/namespace_packages.txt
odoo8_addon_sale_payment_method_automatic_workflow-8.0.1.0.0.99.dev21.dist-info/top_level.txt
odoo8_addon_sale_payment_method_automatic_workflow-8.0.1.0.0.99.dev21.dist-info/RECORD
