Metadata-Version: 2.1
Name: odoo8-addon-sale-payment-method-automatic-workflow
Version: 8.0.1.0.0.99.dev21
Summary: Sale Payment Method - Automatic Worflow (link module)
Home-page: http://www.camptocamp.com
Author: Camptocamp,Akretion,Odoo Community Association (OCA)
Author-email: support@odoo-community.org
License: AGPL-3
Platform: UNKNOWN
Classifier: Programming Language :: Python
Classifier: Framework :: Odoo
Classifier: Framework :: Odoo :: 8.0
Classifier: License :: OSI Approved :: GNU Affero General Public License v3
Requires-Python: ~=2.7
Requires-Dist: odoo8-addon-sale-automatic-workflow
Requires-Dist: odoo8-addon-sale-payment-method
Requires-Dist: odoo (<9.0a,>=8.0a)
